zcompact/__init__.py
zcompact/archive.py
zcompact/exceptions.py
zcompact-1.0.1.dist-info/METADATA
zcompact-1.0.1.dist-info/WHEEL
zcompact-1.0.1.dist-info/top_level.txt
zcompact-1.0.1.dist-info/RECORD
