Metadata-Version: 2.4
Name: zcompact
Version: 1.0.1
Summary: Python wrapper for zcompact - JSON compaction with queryable ID index
Author: Zack Marks
License: MIT
Project-URL: Homepage, https://github.com/zzmarks26/Zcompact
Project-URL: Repository, https://github.com/zzmarks26/Zcompact
Project-URL: Issues, https://github.com/zzmarks26/Zcompact/issues
Keywords: json,compression,archive,index,query
Classifier: Development Status :: 4 - Beta
Classifier: Intended Audience :: Developers
Classifier: License :: OSI Approved :: MIT License
Classifier: Programming Language :: Python :: 3
Classifier: Programming Language :: Python :: 3.8
Classifier: Programming Language :: Python :: 3.9
Classifier: Programming Language :: Python :: 3.10
Classifier: Programming Language :: Python :: 3.11
Classifier: Programming Language :: Python :: 3.12
Classifier: Topic :: Database
Classifier: Topic :: System :: Archiving :: Compression
Requires-Python: >=3.8
